igrafx_mining_sdk/__init__.py
igrafx_mining_sdk/api_connector.py
igrafx_mining_sdk/column_mapping.py
igrafx_mining_sdk/datasource.py
igrafx_mining_sdk/graph.py
igrafx_mining_sdk/jars/avatica-1.26.0.jar
igrafx_mining_sdk/project.py
igrafx_mining_sdk/workgroup.py
igrafx_mining_sdk-2.37.1.dist-info/METADATA
igrafx_mining_sdk-2.37.1.dist-info/WHEEL
igrafx_mining_sdk-2.37.1.dist-info/licenses/LICENSE
igrafx_mining_sdk-2.37.1.dist-info/licenses/LICENSES/Apache-2.0.txt
igrafx_mining_sdk-2.37.1.dist-info/licenses/NOTICE
igrafx_mining_sdk-2.37.1.dist-info/RECORD
