Metadata-Version: 2.4
Name: igrafx_mining_sdk
Version: 2.37.1
Summary: The iGrafx P360 Live Mining SDK is an open source application that can be used to manage your mining projects.
License: MIT
License-File: LICENSE
License-File: LICENSES/Apache-2.0.txt
License-File: NOTICE
Keywords: process mining
Author: iGrafx
Author-email: contact@igrafx.com
Requires-Python: >=3.10.0,<3.13
Classifier: License :: OSI Approved :: MIT License
Classifier: Programming Language :: Python :: 3
Classifier: Programming Language :: Python :: 3.10
Classifier: Programming Language :: Python :: 3.11
Classifier: Programming Language :: Python :: 3.12
Requires-Dist: SQLAlchemy (==2.0.44)
Requires-Dist: jaydebeapi (>=1.2.3,<2.0.0)
Requires-Dist: jpype1 (==1.5.0)
Requires-Dist: networkx (>=3.0.0,<3.3.0)
Requires-Dist: numpy (>=1.25.0,<2.0.0)
Requires-Dist: pandas (>=2.0.0,<=2.2.1)
Requires-Dist: pip (==25.3.0)
Requires-Dist: pydruid (==0.6.9)
Requires-Dist: python-dotenv (==1.2.1)
Requires-Dist: requests (==2.32.5)
Requires-Dist: setuptools (==80.9.0)
Requires-Dist: toml (==0.10.2)
Requires-Dist: urllib3 (==2.5.0)
Project-URL: Homepage, https://www.igrafx.com/
Project-URL: Repository, https://github.com/igrafx/mining-python-sdk
